buttercoin/exceptions.py
buttercoin/client.py
buttercoin/api.py
buttercoin/__init__.py
buttercoin-1.0.2.dist-info/top_level.txt
buttercoin-1.0.2.dist-info/METADATA
buttercoin-1.0.2.dist-info/RECORD
buttercoin-1.0.2.dist-info/metadata.json
buttercoin-1.0.2.dist-info/WHEEL
buttercoin-1.0.2.dist-info/DESCRIPTION.rst
buttercoin-1.0.2.dist-info/PKG-INFO~
