Metadata-Version: 2.0
Name: buttercoin
Version: 1.0.2
Summary: Buttercoin API Python Client
Home-page: https://github.com/buttercoin/buttercoin-python
Author: Buttercoin
Author-email: api@buttercoin.com
License: MIT
Keywords: bitcoin,buttercoin,trading platform,cryptocurrency,digital currency,btc
Platform: Posix; MacOS X; Windows
Classifier: Development Status :: 5 - Production/Stable
Classifier: Intended Audience :: Developers
Classifier: License :: OSI Approved :: MIT License
Classifier: Operating System :: OS Independent
Classifier: Topic :: Internet
Classifier: Programming Language :: Python :: 2
Classifier: Programming Language :: Python :: 2.6
Classifier: Programming Language :: Python :: 2.7
Classifier: Programming Language :: Python :: 3
Classifier: Programming Language :: Python :: 3.3
Classifier: Programming Language :: Python :: 3.4
Requires-Dist: requests
